{
  "loader": "forge:separate_transforms",
  "gui_light": "front",
  "base": {
    "parent": "enigmaticlegacy:item/infernal_shield_item"
  },
  "perspectives": {
    "firstperson_righthand": {
      "parent": "enigmaticlegacy:item/infernal_shield_blocking_model"
    },
    "firstperson_lefthand": {
      "parent": "enigmaticlegacy:item/infernal_shield_blocking_model"
    },
    "thirdperson_righthand": {
      "parent": "enigmaticlegacy:item/infernal_shield_blocking_model"
    },
    "thirdperson_lefthand": {
      "parent": "enigmaticlegacy:item/infernal_shield_blocking_model"
    },
    "head": {
      "parent": "enigmaticlegacy:item/infernal_shield_blocking_model"
    }
  }
}